datata_entryiz/__init__.py
datata_entryiz/main.py
datata_entryiz/utils.py
datata_entryiz-0.1.1.dist-info/METADATA
datata_entryiz-0.1.1.dist-info/WHEEL
datata_entryiz-0.1.1.dist-info/RECORD
